fun_apis/__init__.py
fun_apis/main.py
fun_apis/api_clients/__init__.py
fun_apis/api_clients/animal_client.py
fun_apis/api_clients/celebrity_client.py
fun_apis/api_clients/fact_client.py
fun_apis/api_clients/quote_client.py
fun_apis/api_clients/superhero_client.py
fun_apis/cli/__init__.py
fun_apis/cli/interactive.py
fun_apis/config/__init__.py
fun_apis/config/config_manager.py
fun_apis/constants/__init__.py
fun_apis/constants/general.py
fun_apis/constants/interactive.py
fun_apis/constants/types.py
fun_apis/constants/data/heroes_ids_names.json
fun_apis/utils/__init__.py
fun_apis/utils/formatting.py
fun_apis/utils/https_interaction.py
fun_apis/utils/other.py
fun_apis/utils/validation.py
fun_apis_cli-1.0.2.dist-info/licenses/LICENSE
fun_apis_cli-1.0.2.dist-info/METADATA
fun_apis_cli-1.0.2.dist-info/WHEEL
fun_apis_cli-1.0.2.dist-info/entry_points.txt
fun_apis_cli-1.0.2.dist-info/top_level.txt
fun_apis_cli-1.0.2.dist-info/RECORD
