Metadata-Version: 2.4
Name: fun-apis-cli
Version: 1.0.2
Summary: A fun Python CLI tool for fetching random facts, animal information, quotes, and much more from various APIs.
Author-email: Taha Yasser Adnan <taha.y.adnan@gmail.com>
License: MIT License
Project-URL: Homepage, https://github.com/tahadnan/Fun-APIs-CLI
Project-URL: Repository, https://github.com/tahadnan/Fun-APIs-CLI
Keywords: APIs,CLI,fun apis
Classifier: Development Status :: 5 - Production/Stable
Classifier: Programming Language :: Python :: 3
Classifier: License :: OSI Approved :: MIT License
Classifier: Operating System :: OS Independent
Classifier: Natural Language :: English
Requires-Python: >=3.13
License-File: LICENSE
Requires-Dist: platformdirs>=4.3.8
Requires-Dist: plotext>=5.3.2
Requires-Dist: prompt-toolkit>=3.0.51
Requires-Dist: pycountry>=24.6.1
Requires-Dist: requests>=2.32.4
Requires-Dist: rich>=14.0.0
Requires-Dist: ruff>=0.12.0
Requires-Dist: twine>=6.1.0
Dynamic: license-file
